njsCore/__init__.py
njsCore/Color/Color.py
njsCore/Color/ColorUtility.py
njsCore/Color/__init__.py
njsCore/Vector/Vector.py
njsCore/Vector/__init__.py
NJS-0.0.5.2.dist-info/LICENSE
NJS-0.0.5.2.dist-info/METADATA
NJS-0.0.5.2.dist-info/WHEEL
NJS-0.0.5.2.dist-info/top_level.txt
NJS-0.0.5.2.dist-info/RECORD
