Metadata-Version: 2.1
Name: NJS
Version: 0.0.5.2
Summary: njs core
Home-page: https://github.com/NamjuLee
Author: NJ Namju Lee
Author-email: nj.namju@gmail.com
License: MIT
Platform: UNKNOWN
Classifier: Programming Language :: Python :: 3
Classifier: License :: OSI Approved :: MIT License
Classifier: Operating System :: OS Independent
License-File: LICENSE
